CharNetOCR/__init__.py
CharNetOCR/main.py
CharNetOCR/models/CharNetDC.pt
CharNetOCR/models/CharNetLC.pt
CharNetOCR/models/CharNetUC.pt
CharNetOCR/models/__init__.py
CharNetOCR/temp/__init__.py
CharNetOCR/utils/__init__.py
CharNetOCR/utils/bboxes.py
CharNetOCR/utils/detection.py
CharNetOCR/utils/misc.py
charnetocr-1.0.0.dist-info/METADATA
charnetocr-1.0.0.dist-info/WHEEL
charnetocr-1.0.0.dist-info/top_level.txt
charnetocr-1.0.0.dist-info/RECORD
