Metadata-Version: 2.2
Name: CharNetOCR
Version: 1.0.0
Requires-Dist: ultralytics
Requires-Dist: opencv-python
Requires-Dist: numpy
Dynamic: requires-dist
